geoimage_heic/__init__.py
geoimage_heic/main.py
geoimage_heic/fonts/Arimo-VariableFont_wght.ttf
geoimage_heic/fonts/__init__.py
geoimage_heic-1.6.dist-info/LICENSE
geoimage_heic-1.6.dist-info/METADATA
geoimage_heic-1.6.dist-info/WHEEL
geoimage_heic-1.6.dist-info/entry_points.txt
geoimage_heic-1.6.dist-info/top_level.txt
geoimage_heic-1.6.dist-info/RECORD
