Metadata-Version: 2.1
Name: geoimage_heic
Version: 1.6
Summary: Add Latitude and Longitude to HEIC images
Author: Gerard Weatherby
Author-email: gerardw@alum.mit.edu
License: MIT
Requires-Python: >=3.12
License-File: LICENSE
Requires-Dist: pillow
Requires-Dist: pillow-heif
Requires-Dist: piexif
